dmm_api/__init__.py
dmm_api/client.py
dmm_api/common.py
dmm_api/crawler.py
dmm_api-0.1.4.dist-info/LICENSE
dmm_api-0.1.4.dist-info/WHEEL
dmm_api-0.1.4.dist-info/METADATA
dmm_api-0.1.4.dist-info/RECORD
