Metadata-Version: 2.1
Name: dmm-api
Version: 0.1.4
Summary: DMM API Client for Python
Home-page: https://github.com/takelushi/dmm-api-py
License: MIT
Author: Takeru Saito
Author-email: takelushi@gmail.com
Maintainer: Takeru Saito
Maintainer-email: takelushi@gmail.com
Requires-Python: >=3.7,<4.0
Classifier: License :: OSI Approved :: MIT License
Classifier: Programming Language :: Python :: 3
Classifier: Programming Language :: Python :: 3.7
Classifier: Programming Language :: Python :: 3.8
Classifier: Programming Language :: Python :: 3.9
Requires-Dist: requests (==2.23.0)
Project-URL: Repository, https://github.com/takelushi/dmm-api-py
Project-URL: issues, https://github.com/takelushi/dmm-api-py/issues
